mylabcopier/__init__.py
mylabcopier/labs.py
lab10lol-1.0.1.dist-info/METADATA
lab10lol-1.0.1.dist-info/WHEEL
lab10lol-1.0.1.dist-info/top_level.txt
lab10lol-1.0.1.dist-info/RECORD
